[
  {
    "email": "michel.dupont@gmail.com",
    "password": "hash",
    "passwordConfirmation": "hash",
    "firstname": "Michel",
    "lastname": "Dupont",
    "about": "Salut moi c'est Michel ! Passioné par le sport j'ai hâte de partager des activités avec vous",
    "address": "25 rue de la boulangerie",
    "zip_code": "13000",
    "city": "Marseille",
    "country": "France",
    "cookie": "true",
    "landmark": "false",
    "coordinate": "[]"
  },
  {
    "email": "jerome24@gmail.com",
    "password": "hash",
    "passwordConfirmation": "hash",
    "firstname": "Jerome",
    "lastname": "Cheval",
    "about": "Jerome 29 ans passioné de Tennis",
    "address": "8 boulevard de la fraise",
    "zip_code": "37000",
    "city": "Tours",
    "country": "France",
    "cookie": "true",
    "landmark": "false",
    "coordinate": "[]"
  },
  {
    "email": "juliettedu34@gmail.com",
    "password": "hash",
    "passwordConfirmation": "hash",
    "firstname": "Juliette",
    "lastname": "Durand",
    "about": "Hello moi c'est Juliette, 36 ans fan de jeu de role",
    "address": "7 square Paul Lescure",
    "zip_code": "21000",
    "city": "Dijon",
    "country": "France",
    "cookie": "true",
    "landmark": "false",
    "coordinate": "[]"
  },

  {
    "email": "alexandre.lee@gmail.com",
    "password": "hash",
    "passwordConfirmation": "hash",
    "firstname": "Michel",
    "lastname": "Dupont",
    "about": "Salut moi c'est Alexandre ! Passioné par le sport j'ai hâte de partager des activités avec vous",
    "address": "25 rue de la forge",
    "zip_code": "69000",
    "city": "Lyon",
    "country": "France",
    "cookie": "true",
    "landmark": "false",
    "coordinate": "[]"
  },
  {
    "email": "clem24@gmail.com",
    "password": "hash",
    "passwordConfirmation": "hash",
    "firstname": "Clemence",
    "lastname": "Girerd",
    "about": "Clemence 19 ans passioné de Velo",
    "address": "8 avenue de la truffe",
    "zip_code": "96000",
    "city": "Lille",
    "country": "France",
    "cookie": "true",
    "landmark": "false",
    "coordinate": "[]"
  },
  {
    "email": "laurencedu25@gmail.com",
    "password": "hash",
    "passwordConfirmation": "hash",
    "firstname": "Laurence",
    "lastname": "Blanc",
    "about": "Hello moi c'est Laurence, 546 ans fan de bridge",
    "address": "7 square Paul Bocuse",
    "zip_code": "25000",
    "city": "Besançon",
    "country": "France",
    "cookie": "true",
    "landmark": "false",
    "coordinate": "[]"
  },

  {
    "email": "kevin.smith@gmail.com",
    "password": "hash",
    "passwordConfirmation": "hash",
    "firstname": "Kevin",
    "lastname": "Smith",
    "about": "Salut moi c'est Kevin ! Passioné par le sport j'ai hâte de partager des activités avec vous",
    "address": "8 rue du volcan",
    "zip_code": "10000",
    "city": "Bruxelles",
    "country": "Belgique",
    "cookie": "true",
    "landmark": "false",
    "coordinate": "[]"
  },
  {
    "email": "paul35@gmail.com",
    "password": "hash",
    "passwordConfirmation": "hash",
    "firstname": "Paul",
    "lastname": "Bismuth",
    "about": "Paul 29 ans passioné de Bilboquet",
    "address": "8 boulevard de la pomme de terre",
    "zip_code": "35000",
    "city": "Rennes",
    "country": "France",
    "cookie": "true",
    "landmark": "false",
    "coordinate": "[]"
  },
  {
    "email": "juliedu42@gmail.com",
    "password": "hash",
    "passwordConfirmation": "hash",
    "firstname": "Julie",
    "lastname": "Poulpe",
    "about": "Hello moi c'est Julie, 36 ans fan d'echecs",
    "address": "7 square Paul Lescure",
    "zip_code": "42000",
    "city": "Saint-Etienne",
    "country": "France",
    "cookie": "true",
    "landmark": "false",
    "coordinate": "[]"
  },
  {
    "email": "karl.marx@gmail.com",
    "password": "hash",
    "passwordConfirmation": "hash",
    "firstname": "Karl",
    "lastname": "Marx",
    "about": "Salut moi c'est Karl ! Passioné par le sport j'ai hâte de partager des activités avec vous",
    "address": "25 rue de la Russie",
    "zip_code": "14000",
    "city": "Cean",
    "country": "France",
    "cookie": "true",
    "landmark": "false",
    "coordinate": "[]"
  }
]
